[
    {
        "timestamp": "2026-05-06T12:29:15.013890",
        "input": "start trading",
        "intent": "unrecognized",
        "status": "failed"
    },
    {
        "timestamp": "2026-05-06T12:45:34.844798",
        "input": "start trade",
        "intent": "trading_symbols",
        "status": "completed"
    },
    {
        "timestamp": "2026-05-06T12:48:23.858849",
        "input": "scan",
        "intent": "unrecognized",
        "status": "failed"
    },
    {
        "timestamp": "2026-05-06T12:57:29.717583",
        "input": "scan",
        "intent": "bulk_scan",
        "status": "completed"
    },
    {
        "timestamp": "2026-05-06T14:17:25.960493",
        "input": "scan",
        "intent": "bulk_scan",
        "status": "completed"
    },
    {
        "timestamp": "2026-05-06T14:20:26.232722",
        "input": "scan",
        "intent": "bulk_scan",
        "status": "completed"
    },
    {
        "timestamp": "2026-05-06T14:34:01.199774",
        "input": "scan",
        "intent": "bulk_scan",
        "status": "completed"
    },
    {
        "timestamp": "2026-05-06T14:54:23.679694",
        "input": "scan",
        "intent": "bulk_scan",
        "status": "completed"
    },
    {
        "timestamp": "2026-05-06T15:11:18.412554",
        "input": "scan",
        "intent": "bulk_scan",
        "status": "completed"
    },
    {
        "timestamp": "2026-05-06T15:13:23.642056",
        "input": "scan",
        "intent": "bulk_scan",
        "status": "completed"
    },
    {
        "timestamp": "2026-05-06T15:16:14.580923",
        "input": "scan",
        "intent": "bulk_scan",
        "status": "completed"
    },
    {
        "timestamp": "2026-05-06T15:18:51.805645",
        "input": "scan",
        "intent": "bulk_scan",
        "status": "completed"
    }
]